paprika_connector/__init__.py
paprika_connector/connectors/__init__.py
paprika_connector/connectors/connector.py
paprika_connector/connectors/connector_factory.py
paprika_connector/connectors/datasource_builder.py
paprika_connector/connectors/helper.py
paprika_connector/connectors/mssql_connector.py
paprika_connector/connectors/mysql_connector.py
paprika_connector/connectors/odbc_connector.py
paprika_connector/connectors/postgresql_connector.py
paprika_connector/connectors/repository.py
paprika_connector/system/__init__.py
paprika_connector/system/connection_string_builders.py
paprika_connector/system/formatters.py
paprika_connector/system/ora.py
paprika_connector/system/strings.py
paprika_connector-0.0.6.dist-info/LICENSE
paprika_connector-0.0.6.dist-info/METADATA
paprika_connector-0.0.6.dist-info/WHEEL
paprika_connector-0.0.6.dist-info/top_level.txt
paprika_connector-0.0.6.dist-info/RECORD
